polytope/__init__.py
polytope/version.py
polytope/api/Admin.py
polytope/api/Auth.py
polytope/api/Client.py
polytope/api/CollectionVisitor.py
polytope/api/Config.py
polytope/api/RequestManager.py
polytope/api/Result.py
polytope/api/__init__.py
polytope/api/config_schema.json
polytope/api/helpers.py
polytope/cli/__init__.py
polytope/cli/cli.py
polytope/cli/binders/__init__.py
polytope/cli/binders/admin.py
polytope/cli/binders/auth.py
polytope/cli/binders/collection.py
polytope/cli/binders/config.py
polytope/cli/binders/helpers.py
polytope/cli/binders/request.py
polytope_client-0.7.8.dist-info/licenses/LICENSE.txt
polytope_client-0.7.8.dist-info/METADATA
polytope_client-0.7.8.dist-info/WHEEL
polytope_client-0.7.8.dist-info/entry_points.txt
polytope_client-0.7.8.dist-info/top_level.txt
polytope_client-0.7.8.dist-info/RECORD
