Metadata-Version: 2.4
Name: polytope-client
Version: 0.7.8
Summary: A Python and command-line client to communicate with a Polytope API server.
Author-email: ECMWF <software.support@ecmwf.int>
License-Expression: Apache-2.0
Project-URL: Homepage, https://github.com/ecmwf-projects/polytope-client
Classifier: Development Status :: 4 - Beta
Classifier: Intended Audience :: Developers
Classifier: Intended Audience :: Science/Research
Classifier: Natural Language :: English
Classifier: Operating System :: POSIX :: Linux
Classifier: Programming Language :: Python
Classifier: Programming Language :: Python :: 3 :: Only
Classifier: Programming Language :: Python :: 3.9
Classifier: Programming Language :: Python :: 3.10
Classifier: Programming Language :: Python :: 3.11
Classifier: Programming Language :: Python :: 3.12
License-File: LICENSE.txt
Requires-Dist: Click
Requires-Dist: requests
Requires-Dist: pyyaml
Requires-Dist: jsonschema
Requires-Dist: docstring_parser
Requires-Dist: tqdm
Dynamic: license-file
